__init__.py
bootstrap_ci.py
bootstrap_ci-0.0.1.dist-info/LICENSE
bootstrap_ci-0.0.1.dist-info/METADATA
bootstrap_ci-0.0.1.dist-info/WHEEL
bootstrap_ci-0.0.1.dist-info/top_level.txt
bootstrap_ci-0.0.1.dist-info/RECORD
