Metadata-Version: 2.1
Name: bootstrap-ci
Version: 0.0.1
Summary: Bootstrap sampling and confidence interval estimation package.
Author-email: Urša Zrimšek <ursazrimsek@gmail.com>
Maintainer-email: Urša Zrimšek <ursazrimsek@gmail.com>
License: MIT License
Project-URL: Homepage, https://github.com/zrimseku/bootstrap-ci
Project-URL: Bug Reports, https://github.com/zrimseku/bootstrap-ci/issues
Keywords: uncertainty,bootstrap,confidence intervals
Requires-Python: >=3.9
License-File: LICENSE
Requires-Dist: numpy >=1.22
Requires-Dist: numba >=0.53
Requires-Dist: scipy >=1.9
Requires-Dist: matplotlib >=3.5
